rocketdive.py
setup.py
rocketdive.egg-info/PKG-INFO
rocketdive.egg-info/SOURCES.txt
rocketdive.egg-info/dependency_links.txt
rocketdive.egg-info/requires.txt
rocketdive.egg-info/top_level.txt