Metadata-Version: 1.0
Name: rocketdive
Version: 0.2
Summary: Easy GUI frontend for Rocket, a modern WSGI web server.
Home-page: http://bitbucket.org/dahlia/rocketdive
Author: Hong, MinHee
Author-email: minhee@dahlia.kr
License: MIT License
Platform: UNKNOWN
